[
  {
    "name": "Next.js",
    "shortname": "nextjs",
    "url": "https://nextjs.org",
    "file": "nextjs.svg",
    "categories": ["Frontend", "Fullstack"],
    "tags": ["SSG", "SSR", "SPA", "ISR", "Serverless"],
    "type": "Framework"
  },
  {
    "name": "Matlab",
    "shorname": "matlab",
    "url": "https://www.mathworks.com/products/matlab.html",
    "file": "matlab.svg",
    "categories": ["Data analyst", "Data science", "Machine learning", "Algorithmic"],
    "tags": "",
    "type": "Language"
  },
  {
    "name": "",
    "shorname": "",
    "url": "",
    "file": "",
    "categories": "",
    "tags": "",
    "type": "Framework"
  },
  {
    "name": "",
    "shorname": "",
    "url": "",
    "file": "",
    "categories": "",
    "tags": "",
    "type": "Framework"
  },
  {
    "name": "",
    "shorname": "",
    "url": "",
    "file": "",
    "categories": "",
    "tags": "",
    "type": "Framework"
  }
]
